czech_number_utils/__init__.py
czech_number_utils-1.0.3.dist-info/LICENSE
czech_number_utils-1.0.3.dist-info/METADATA
czech_number_utils-1.0.3.dist-info/WHEEL
czech_number_utils-1.0.3.dist-info/top_level.txt
czech_number_utils-1.0.3.dist-info/RECORD
