Metadata-Version: 2.1
Name: czech-number-utils
Version: 1.0.3
Summary: Convert numbers to Czech text representations
Home-page: https://github.com/zbyso23/czech-number-utils
Author: Zbigniew Lipka
Author-email: z.lipka@seznam.cz
License: UNKNOWN
Platform: UNKNOWN
Classifier: Programming Language :: Python :: 3
Classifier: License :: OSI Approved :: MIT License
Classifier: Operating System :: OS Independent
Requires-Python: >=3.6
License-File: LICENSE
